[
    {
        "id": 1,
        "url": "Zf2.jpg"
    },
    {
        "id": 2,
        "url": "Zf3.jpg"
    },
    {
        "id": 3,
        "url": "Zf4.jpg"
    },
    {
        "id": 4,
        "url": "https://via.placeholder.com/300?text=Image+4"
    },
    {
        "id": 5,
        "url": "https://via.placeholder.com/300?text=Image+5",
        "title": "Image 5"
    },
    {
        "id": 6,
        "url": "https://via.placeholder.com/300?text=Image+6",
        "title": "Image 6"
    },
    {
        "id": 7,
        "url": "https://via.placeholder.com/300?text=Image+7",
        "title": "Image 7"
    }
]